odoo/addons/purchase_order_product_recommendation_classification/README.rst
odoo/addons/purchase_order_product_recommendation_classification/__init__.py
odoo/addons/purchase_order_product_recommendation_classification/__manifest__.py
odoo/addons/purchase_order_product_recommendation_classification/i18n/purchase_order_product_recommendation_classification.pot
odoo/addons/purchase_order_product_recommendation_classification/readme/CONTRIBUTORS.rst
odoo/addons/purchase_order_product_recommendation_classification/readme/DESCRIPTION.rst
odoo/addons/purchase_order_product_recommendation_classification/readme/USAGE.rst
odoo/addons/purchase_order_product_recommendation_classification/static/description/icon.png
odoo/addons/purchase_order_product_recommendation_classification/static/description/index.html
odoo/addons/purchase_order_product_recommendation_classification/tests/__init__.py
odoo/addons/purchase_order_product_recommendation_classification/tests/test_recommendation.py
odoo/addons/purchase_order_product_recommendation_classification/wizard/__init__.py
odoo/addons/purchase_order_product_recommendation_classification/wizard/purchase_order_recommendation.py
odoo/addons/purchase_order_product_recommendation_classification/wizard/purchase_order_recommendation_view.xml
odoo13_addon_purchase_order_product_recommendation_classification-13.0.1.0.1.dev3.dist-info/METADATA
odoo13_addon_purchase_order_product_recommendation_classification-13.0.1.0.1.dev3.dist-info/WHEEL
odoo13_addon_purchase_order_product_recommendation_classification-13.0.1.0.1.dev3.dist-info/top_level.txt
odoo13_addon_purchase_order_product_recommendation_classification-13.0.1.0.1.dev3.dist-info/RECORD
